{
  "title": "Walk Away",
  "title_raw": "Walk Away",
  "version": null,
  "artist": "Dia Frampton",
  "group_key": "walk away|dia frampton",
  "writers": {
    "lyricist": "Dia Frampton/Jimmy Harry/Fran Hal",
    "composer": "Ian Kirkpatrick",
    "arranger": null
  },
  "lyrics": [
    {
      "time": 9.98,
      "time_str": "00:09.980",
      "text": "Looking back on younger days, the time has passed,",
      "translation": "回顾年少时候的那段时光，一切都已过去"
    },
    {
      "time": 13.57,
      "time_str": "00:13.570",
      "text": "And nothing stays the same. Hey hey hey!",
      "translation": "一切都已改变。嘿 嘿 嘿"
    },
    {
      "time": 18.64,
      "time_str": "00:18.640",
      "text": "She was such a pretty girl,",
      "translation": "她是如此美的小女孩"
    },
    {
      "time": 21.8,
      "time_str": "00:21.800",
      "text": "With glowing eyes and yellow curls. Hey hey hey!",
      "translation": "她有着闪闪发亮的眼睛和一头金黄色的卷发 嘿 嘿 嘿"
    },
    {
      "time": 27.66,
      "time_str": "00:27.660",
      "text": "Stars are in a summer night,",
      "translation": "在那星空下的夏夜"
    },
    {
      "time": 29.76,
      "time_str": "00:29.760",
      "text": "She's wishing that they'd fall down through the atmosphere,",
      "translation": "她希望那些人能够下地狱"
    },
    {
      "time": 33.16,
      "time_str": "00:33.160",
      "text": "For a souvenir.",
      "translation": "以此来祭奠（她所受的伤害）"
    },
    {
      "time": 36.6,
      "time_str": "00:36.600",
      "text": "She's waiting for her Superman, her Never land,",
      "translation": "她等待她的超人能够来临，带她去永无之乡"
    },
    {
      "time": 39.38,
      "time_str": "00:39.380",
      "text": "Cause he can show the way. Hey hey hey!",
      "translation": "他知道该如何去那里。嘿 嘿 嘿"
    },
    {
      "time": 44.1,
      "time_str": "00:44.100",
      "text": "Where's her missing piece her mind's been chasing, chasing?",
      "translation": "那已迷失的，她内心一直所追寻的地方在哪里"
    },
    {
      "time": 52.27,
      "time_str": "00:52.270",
      "text": "A bullet with your name, a ticking time grenade,",
      "translation": "一粒已瞄准的子弹，一颗定时炸弹"
    },
    {
      "time": 56.67,
      "time_str": "00:56.670",
      "text": "You better run away, run away, run away",
      "translation": "你们无处可逃 无处可逃 无处可逃"
    },
    {
      "time": 61.22,
      "time_str": "01:01.220",
      "text": "Either way you're screwed, there's nothing you can do,",
      "translation": "你们所有的挣扎都是徒劳"
    },
    {
      "time": 65.45,
      "time_str": "01:05.450",
      "text": "You better run away, run away, run away.",
      "translation": "你们无处可逃 无处可逃 无处可逃"
    },
    {
      "time": 79.6,
      "time_str": "01:19.600",
      "text": "She's tellin' tales through telephone",
      "translation": "她透过电话告诉你们一切"
    },
    {
      "time": 81.99,
      "time_str": "01:21.990",
      "text": "That make you cry, chill to the bone. Hey hey hey!",
      "translation": "这使你们害怕到哭泣，那恐惧渗入骨髓 嘿 嘿 嘿"
    },
    {
      "time": 88.34,
      "time_str": "01:28.340",
      "text": "It's lock and key, electrified,",
      "translation": "一切都在掌控之中"
    },
    {
      "time": 91.13,
      "time_str": "01:31.130",
      "text": "Hide and seek from dirty eyes. Hey hey hey!",
      "translation": "你们那那肮脏的眼睛里还想躲藏些什么 嘿 嘿 嘿"
    },
    {
      "time": 97.6,
      "time_str": "01:37.600",
      "text": "Driving in the rain to somewhere far,",
      "translation": "冒着大雨想开车离去，远离这里"
    },
    {
      "time": 100.11,
      "time_str": "01:40.110",
      "text": "But they've got tattoos stamped upon their arms, of her name in hearts",
      "translation": "但他们却不知自己的双手却早已满是罪证  对她的名字刻骨铭心"
    },
    {
      "time": 105.99,
      "time_str": "01:45.990",
      "text": "She doesn't understand that love is what you give, not given up.",
      "translation": "她无法理解爱是被给予 而不是被放弃"
    },
    {
      "time": 110.479,
      "time_str": "01:50.479",
      "text": "Hey hey hey!",
      "translation": "嘿 嘿 嘿"
    },
    {
      "time": 114.0,
      "time_str": "01:54.000",
      "text": "Where's her missing piece her mind's been chasing, chasing?",
      "translation": "那已迷失的，她内心一直所追寻的地方在哪里"
    },
    {
      "time": 122.3,
      "time_str": "02:02.300",
      "text": "A bullet with your name, a ticking time grenade,",
      "translation": "一粒已瞄准的子弹，一颗定时炸弹"
    },
    {
      "time": 126.55,
      "time_str": "02:06.550",
      "text": "You better run away, run away, run away",
      "translation": "你们无处可逃 无处可逃 无处可逃"
    },
    {
      "time": 131.8,
      "time_str": "02:11.800",
      "text": "Either way you're screwed, there's nothing you can do,",
      "translation": "你们所有的挣扎都是徒劳"
    },
    {
      "time": 135.24,
      "time_str": "02:15.240",
      "text": "No matter what you say, what you say, what you say.",
      "translation": "说什么都于事无补 于事无补 于事无补"
    },
    {
      "time": 157.27,
      "time_str": "02:37.270",
      "text": "Yeah you better not sleep, because she's waiting, waiting.",
      "translation": "你最好不要就这么睡去，她像猎人等待猎物般在等待着你"
    },
    {
      "time": 168.27,
      "time_str": "02:48.270",
      "text": "She knows all about you; you're in her aim.",
      "translation": "她知道你们的一切 你们是她的目标"
    },
    {
      "time": 181.51,
      "time_str": "03:01.510",
      "text": "A bullet with your name, a ticking time grenade,",
      "translation": "一粒已瞄准的子弹，一颗定时炸弹"
    },
    {
      "time": 185.37,
      "time_str": "03:05.370",
      "text": "You better run away, run away, run away",
      "translation": "你们无处可逃 无处可逃 无处可逃"
    },
    {
      "time": 190.75,
      "time_str": "03:10.750",
      "text": "Either way you're screwed, there's nothing you can do,",
      "translation": "你们所有的挣扎都是徒劳"
    },
    {
      "time": 194.92,
      "time_str": "03:14.920",
      "text": "You better run away, run away, run away",
      "translation": "你们无处可逃 无处可逃 无处可逃"
    },
    {
      "time": 198.16,
      "time_str": "03:18.160",
      "text": "A bullet with your name, a ticking time grenade,",
      "translation": "一粒已瞄准的子弹，一颗定时炸弹"
    },
    {
      "time": 203.74,
      "time_str": "03:23.740",
      "text": "You better run away, run away, run away",
      "translation": "你们无处可逃 无处可逃 无处可逃"
    },
    {
      "time": 207.12,
      "time_str": "03:27.120",
      "text": "Either way you're screwed, there's nothing you can do,",
      "translation": "你们所有的挣扎都是徒劳"
    },
    {
      "time": 211.36,
      "time_str": "03:31.360",
      "text": "No matter what you say, what you say, what you say.",
      "translation": "说什么都于事无补 于事无补 于事无补"
    }
  ],
  "has_translation": true,
  "source_file": "Walk Away - Dia Frampton.lrc"
}